bomber/__init__.py
bomber/bomber.py
bomber/linux.py
bomber/win.py
bomber/windows.py
haxorbomber-1.0.0.dist-info/LICENSE
haxorbomber-1.0.0.dist-info/METADATA
haxorbomber-1.0.0.dist-info/WHEEL
haxorbomber-1.0.0.dist-info/top_level.txt
haxorbomber-1.0.0.dist-info/RECORD
