Metadata-Version: 2.1
Name: haxorbomber
Version: 1.0.0
Summary: SMS Bomber Project.
Home-page: https://github.com/Aru-Ofc-git/ARU-BOMBER.git
Author: Ariful Islam Arman
Author-email: arifulislamarman02@gmail.com
Project-URL: Bug Tracker, https://github.com/Aru-Ofc-git
Classifier: Development Status :: 5 - Production/Stable
Classifier: Programming Language :: Python :: 3
Classifier: Programming Language :: Python :: 3.5
Classifier: Programming Language :: Python
Classifier: License :: OSI Approved :: MIT License
Classifier: Operating System :: OS Independent
Requires-Python: >=3.6
License-File: LICENSE
